mlpp_features/__init__.py
mlpp_features/accessors.py
mlpp_features/calc.py
mlpp_features/decorators.py
mlpp_features/discover.py
mlpp_features/geo_calculations.py
mlpp_features/nwp.py
mlpp_features/obs.py
mlpp_features/selectors.py
mlpp_features/terrain.py
mlpp_features/time.py
mlpp_features-0.13.0.dist-info/LICENSE
mlpp_features-0.13.0.dist-info/METADATA
mlpp_features-0.13.0.dist-info/WHEEL
mlpp_features-0.13.0.dist-info/RECORD
